build_tools/changelog.py
doc/source/conf.py
examples/standard/plot_em.py
examples/standard/plot_filter.py
examples/standard/plot_missing.py
examples/standard/plot_online.py
examples/standard/plot_sin.py
examples/unscented/plot_additive.py
examples/unscented/plot_filter.py
pykalman/__init__.py
pykalman/_nopytest_tests.py
pykalman/standard.py
pykalman/unscented.py
pykalman/utils_numpy.py
pykalman/datasets/__init__.py
pykalman/datasets/base.py
pykalman/datasets/data/robot.mat
pykalman/datasets/descr/__init__.py
pykalman/datasets/descr/robot.rst
pykalman/sqrt/__init__.py
pykalman/sqrt/bierman.py
pykalman/sqrt/cholesky.py
pykalman/sqrt/unscented.py
pykalman/utils/__init__.py
pykalman/utils/_numpy.py
pykalman/utils/_sklearn.py
pykalman-0.11.1.dist-info/licenses/LICENSE
pykalman-0.11.1.dist-info/METADATA
pykalman-0.11.1.dist-info/WHEEL
pykalman-0.11.1.dist-info/top_level.txt
pykalman-0.11.1.dist-info/zip-safe
pykalman-0.11.1.dist-info/RECORD
