Metadata-Version: 2.4
Name: pykalman
Version: 0.11.1
Summary: An implementation of the Kalman Filter, Kalman Smoother, and EM algorithm in Python
Author: Daniel Duckworth
Author-email: Maksym Balatsko <mbalatsko@gmail.com>, pykalman developers <info@gcos.ai>
Maintainer-email: pykalman developers <info@gcos.ai>
License: All code contained except that in pykalman/utils.py is released under the
Project-URL: Homepage, https://github.com/pykalman/pykalman
Project-URL: Repository, https://github.com/pykalman/pykalman
Project-URL: Documentation, https://pykalman.readthedocs.io/en/latest/
Project-URL: Download, https://pypi.org/project/pykalman/
Keywords: kalman filter,smoothing,filter,smoothing,em,expectation-maximization,hmm,tracking,unscented
Classifier: Development Status :: 4 - Beta
Classifier: Intended Audience :: Science/Research
Classifier: License :: OSI Approved :: BSD License
Classifier: Operating System :: OS Independent
Classifier: Programming Language :: Python
Classifier: Programming Language :: Python :: 3 :: Only
Classifier: Programming Language :: Python :: 3.10
Classifier: Programming Language :: Python :: 3.11
Classifier: Programming Language :: Python :: 3.12
Classifier: Programming Language :: Python :: 3.13
Classifier: Programming Language :: Python :: 3.14
Classifier: Topic :: Scientific/Engineering :: Artificial Intelligence
Requires-Python: <3.15,>=3.10
License-File: LICENSE
Requires-Dist: numpy<3
Requires-Dist: packaging
Requires-Dist: scikit-base<0.14.0
Requires-Dist: scipy<2.0.0
Provides-Extra: tests
Requires-Dist: pytest; extra == "tests"
Provides-Extra: dev
Requires-Dist: pytest; extra == "dev"
Requires-Dist: pre-commit; extra == "dev"
Provides-Extra: docs
Requires-Dist: jupyter; extra == "docs"
Requires-Dist: Sphinx<9.0.0; extra == "docs"
Requires-Dist: numpydoc; extra == "docs"
Requires-Dist: matplotlib; extra == "docs"
Provides-Extra: all
Requires-Dist: jupyter; extra == "all"
Requires-Dist: pytest; extra == "all"
Requires-Dist: Sphinx<9.0.0; extra == "all"
Requires-Dist: numpydoc; extra == "all"
Requires-Dist: twine; extra == "all"
Requires-Dist: pre-commit; extra == "all"
Provides-Extra: numpy1
Requires-Dist: numpy<2; extra == "numpy1"
Dynamic: license-file
